txmongo/__init__.py
txmongo/_bulk.py
txmongo/_bulk_constants.py
txmongo/collection.py
txmongo/connection.py
txmongo/database.py
txmongo/errors.py
txmongo/filter.py
txmongo/gridfs.py
txmongo/protocol.py
txmongo/pymongo_errors.py
txmongo/pymongo_internals.py
txmongo/sessions.py
txmongo/types.py
txmongo/_gridfs/__init__.py
txmongo/_gridfs/errors.py
txmongo/_gridfs/grid_file.py
txmongo/utils/__init__.py
txmongo-25.0.0.dist-info/licenses/LICENSE
txmongo-25.0.0.dist-info/METADATA
txmongo-25.0.0.dist-info/WHEEL
txmongo-25.0.0.dist-info/top_level.txt
txmongo-25.0.0.dist-info/RECORD
