Metadata-Version: 2.4
Name: txmongo
Version: 25.0.0
Summary: Asynchronous Python driver for MongoDB <http://www.mongodb.org>
Home-page: https://github.com/twisted/txmongo
Author: Alexandre Fiori, Bret Curtis
Author-email: fiorix@gmail.com, psi29a@gmail.com
License: Apache License, Version 2.0
Keywords: mongo,mongodb,pymongo,gridfs,txmongo
Classifier: Development Status :: 5 - Production/Stable
Classifier: Intended Audience :: Developers
Classifier: License :: OSI Approved :: Apache Software License
Classifier: Operating System :: MacOS :: MacOS X
Classifier: Operating System :: Microsoft :: Windows
Classifier: Operating System :: POSIX
Classifier: Programming Language :: Python
Classifier: Programming Language :: Python :: 3
Classifier: Programming Language :: Python :: 3.8
Classifier: Programming Language :: Python :: 3.9
Classifier: Programming Language :: Python :: 3.10
Classifier: Programming Language :: Python :: 3.11
Classifier: Programming Language :: Python :: Implementation :: CPython
Classifier: Programming Language :: Python :: Implementation :: PyPy
Classifier: Topic :: Database
License-File: LICENSE
Requires-Dist: twisted>=22.8.0
Requires-Dist: pymongo<=4.10.1,>=3.12
Provides-Extra: srv
Requires-Dist: pymongo[srv]>=3.12; extra == "srv"
Dynamic: author
Dynamic: author-email
Dynamic: classifier
Dynamic: home-page
Dynamic: keywords
Dynamic: license
Dynamic: license-file
Dynamic: provides-extra
Dynamic: requires-dist
Dynamic: summary
